MANIFEST.in
README.rst
setup.py
pysprints/__init__.py
pysprints.egg-info/PKG-INFO
pysprints.egg-info/SOURCES.txt
pysprints.egg-info/dependency_links.txt
pysprints.egg-info/top_level.txt