Metadata-Version: 1.1
Name: pysprints
Version: 1.0.2
Summary: Sprint / Release planning objects
Home-page: http://pypi.python.org/pypi/pysprints
Author: Mark Henwood
Author-email: mark@mcbh.co.uk
License: MIT
Keywords: sprint agile scrum project
Platform: UNKNOWN
Classifier: Development Status :: 5 - Production/Stable
Classifier: Environment :: Plugins
Classifier: Intended Audience :: Developers
Classifier: License :: OSI Approved :: MIT License
Classifier: Natural Language :: English
Classifier: Operating System :: OS Independent
Classifier: Programming Language :: Python :: 2.6
Classifier: Topic :: Utilities
Provides: pysprints
